sampler/__init__.py
sampler/fields.py
sampler/sampler.py
sampler-0.1.dist-info/DESCRIPTION.rst
sampler-0.1.dist-info/METADATA
sampler-0.1.dist-info/metadata.json
sampler-0.1.dist-info/RECORD
sampler-0.1.dist-info/top_level.txt
sampler-0.1.dist-info/WHEEL
