Metadata-Version: 2.0
Name: sampler
Version: 0.1
Summary: Sample data generator for Python
Home-page: UNKNOWN
Author: Sven Perkmann
Author-email: sven.perkmann@gmail.com
License: MIT
Keywords: sampler test data generator
Platform: UNKNOWN
Requires-Dist: fake-factory
